{"AUHRvaYxfJjx9MnCZo4toQ==":"mbr-160x160.png","hcemedOLu5opQK86FJyq4g==":"mbr-1920x1227.jpg","TJx1GMRnAupWSBzSans6lw==":"mbr-122x61.png","2d6jmLxh1Wv98iWUqkwINw==":"mbr-436x245.jpg","I+PpfWrgPxgokfeEpukuAg==":"mbr-436x245.jpeg","RkJBdiLto/vxTiSHLjUEJw==":"mbr-436x291.jpg","HIC+3Zv5u2/akuBJ68BQ/Q==":"mbr-242x242.png","rukk769Qy5w3NqEnDio6tQ==":"mbr-122x122.png","q7wzy8MPC9eBwnm2kzo8pw==":"mbr-122x121.png","ctFySzxnInLxTY7OptT8dA==":"mbr-242x239.png","kcuJdImLMlIG+XEoXxOkvw==":"dji-101-4000x3000.jpg","KHgWs1Kz6omc1vHZUsGisQ==":"dji-100-4000x3000.jpg","SrjR9bUrZfJZFD7q59hj2Q==":"dji-99-4000x3000.jpg","DoMpwKShG9a8j0GTdCwCbg==":"dji-102-4000x3000.jpg","eY7/moab0+TLXuuWUc39bw==":"dji-106-4000x3000.jpg","4UuF+U4xnSCJxgJybmEmeg==":"dji-101-2526x1894.jpg","UAc7kepzJPkrSn4uqTRvmw==":"background4.jpg","zS1+B/6Yyuv2k7UG1TQ99w==":"dji-99-2526x1894.jpg","tq80MgXszaJ5dqcW5M/F7g==":"dji-104-2000x1500.jpg","bhCgVa95bqNrcYaZU03Zyg==":"dji-103-2000x1500.jpg","tT+h+6OMil6uoUXEi+8fzw==":"dji-101-2000x1500.jpg","B8vKpmyJx7pNZZN7vBjmJg==":"dji-102-2000x1500.jpg","f5rv5DoSnxkJVTi9YAT73g==":"dji-105-2000x1500.jpg"}